{"nom": "pas beaucoup", "nbSouris": 3, "nbJours": 3, "nbEssais": 2, "entrainement": false, "tempsMax": "05:00", "dateDebut": "27/03/2020", "sourisDict": {"s0": {"nom": "s0", "essaiDict": {"T0E1": {"isE2": false, "placementPot1": 0.0, "temps": "00:00", "issue": -1}, "T0E2": {"isE2": true, "placementPot1": 0.0, "placementPot2": 0.0, "temps": "00:00", "issue": -1}, "T1E1": {"isE2": false, "placementPot1": 0.0, "temps": "00:00", "issue": -1}, "T1E2": {"isE2": true, "placementPot1": 0.0, "placementPot2": 0.0, "temps": "00:00", "issue": -1}}}, "s1": {"nom": "s1", "essaiDict": {"T0E1": {"isE2": false, "placementPot1": 0.0, "temps": "00:00", "issue": -1}, "T0E2": {"isE2": true, "placementPot1": 0.0, "placementPot2": 0.0, "temps": "00:00", "issue": -1}, "T1E1": {"isE2": false, "placementPot1": 0.0, "temps": "00:00", "issue": -1}, "T1E2": {"isE2": true, "placementPot1": 0.0, "placementPot2": 0.0, "temps": "00:00", "issue": -1}}}, "s2": {"nom": "s2", "essaiDict": {"T0E1": {"isE2": false, "placementPot1": 0.0, "temps": "00:00", "issue": -1}, "T0E2": {"isE2": true, "placementPot1": 0.0, "placementPot2": 0.0, "temps": "00:00", "issue": -1}, "T1E1": {"isE2": false, "placementPot1": 0.0, "temps": "00:00", "issue": -1}, "T1E2": {"isE2": true, "placementPot1": 0.0, "placementPot2": 0.0, "temps": "00:00", "issue": -1}}}}}